Metadata-Version: 2.1
Name: wiseutil
Version: 0.0.1
Summary: Wiseutil
Author: MF
